rttbackend-0.4.3.dist-info/METADATA
rttbackend-0.4.3.dist-info/top_level.txt
rttbackend-0.4.3.dist-info/WHEEL
rttbackend-0.4.3.dist-info/RECORD
rttbackend/types.cpython-39-x86_64-linux-gnu.so
rttbackend/exceptions.py
rttbackend/connection.py
rttbackend/exchange.py
rttbackend/defines.py
rttbackend/config.py
rttbackend/__init__.py
rttbackend/symbols.py
rttbackend/common/transform.py
rttbackend/common/__init__.py
rttbackend/common/flow.py
rttbackend/exchanges/alphavantage.py
rttbackend/exchanges/fmp.py
rttbackend/exchanges/finnhub.py
rttbackend/exchanges/__init__.py
rttbackend/exchanges/mixins/alphavantage_rest.py
rttbackend/exchanges/mixins/fmp_rest.py
rttbackend/exchanges/mixins/__init__.py
rttbackend/exchanges/mixins/finnhub_rest.py
rttbackend/backends/redis.py
rttbackend/backends/postgres.py
rttbackend/backends/__init__.py
