Metadata-Version: 2.1
Name: rttbackend
Version: 0.4.3
Summary: realtimetrade backend service
Home-page: https://github.com/liej6799/realtimetrade
Author: Joes Lie
Author-email: liej6799@protonmail.ch
License: XFree86
Classifier: Intended Audience :: Developers
Classifier: Development Status :: 4 - Beta
Classifier: Programming Language :: Python :: 3 :: Only
Classifier: Programming Language :: Python :: 3.8
Classifier: Programming Language :: Python :: 3.9
Classifier: Programming Language :: Python :: 3.10
Classifier: Framework :: AsyncIO
Requires-Python: >=3.8
Requires-Dist: requests >=2.18.4
Requires-Dist: websockets >=10.0
Requires-Dist: pyyaml
Requires-Dist: aiohttp ==3.8.4
Requires-Dist: aiofile >=2.0.0
Requires-Dist: yapic.json
Requires-Dist: asyncpg
Requires-Dist: numpy ==1.24.4
Requires-Dist: redis
Requires-Dist: pandas
Requires-Dist: uvloop ; platform_system != "Windows"
